pyRDTP/__init__.py
pyRDTP/geometry.py
pyRDTP/geomio.py
pyRDTP/molecule.py
pyRDTP/vaspio.py
pyRDTP/data/__init__.py
pyRDTP/data/colors.py
pyRDTP/data/radius.py
pyRDTP/io/__init__.py
pyRDTP/io/ase.py
pyRDTP/io/vasp.py
pyRDTP/operations/__init__.py
pyRDTP/operations/analysis.py
pyRDTP/operations/benson.py
pyRDTP/operations/combinations.py
pyRDTP/operations/comparisons.py
pyRDTP/operations/graph.py
pyRDTP/operations/identify.py
pyRDTP/operations/md.py
pyRDTP/operations/random_surf.py
pyRDTP/operations/sym_anhilation.py
pyRDTP/operations/sym_anhilation2.py
pyRDTP/operations/symmetry.py
pyRDTP/operations/templates/specifications.json
pyRDTP/tools/__init__.py
pyRDTP/tools/jupyter.py
pyRDTP/tools/pymol.py
pyrdtp-0.2.dist-info/METADATA
pyrdtp-0.2.dist-info/WHEEL
pyrdtp-0.2.dist-info/licenses/LICENSE
pyrdtp-0.2.dist-info/RECORD
