Metadata-Version: 2.1
Name: pyRDTP
Version: 0.2
Summary: Manipulate chemical geometries for heterogeneous catalysis
Project-URL: Homepage, https://gitlab.com/iciq-tcc/nlopez-group/pyrdtp
Author-email: Sergio Pablo García Carrillo <sp.garcia@utoronto.ca>
Maintainer-email: Santiago Morandi <smorandi@iciq.es>, Oliver Loveday <oloveday@iciq.es>
License-File: LICENSE
Keywords: VASP,computational chemistry,heterogeneous catalysis
Classifier: License :: OSI Approved :: MIT License
Classifier: Operating System :: OS Independent
Classifier: Programming Language :: Python :: 3
Requires-Python: >=3.9
Requires-Dist: matplotlib>=3.5.3
Requires-Dist: networkx>=2.8.4
Requires-Dist: numpy>=1.23.3
Requires-Dist: py3dmol>=1.8.1
Requires-Dist: scipy>=1.9.3
Requires-Dist: shapely>=1.4.8
